apxctrl/__init__.py
apxctrl/client.py
apxctrl/controller.py
apxctrl/model.py
apxctrl/server.py
apxctrl-0.5.0.dist-info/METADATA
apxctrl-0.5.0.dist-info/WHEEL
apxctrl-0.5.0.dist-info/entry_points.txt
apxctrl-0.5.0.dist-info/RECORD
