Metadata-Version: 2.4
Name: apxctrl
Version: 0.5.0
Summary: APx500 Control Server - Remote control for Audio Precision test equipment
Requires-Python: >=3.11
Requires-Dist: flask>=3.1.0
Requires-Dist: pydantic>=2.0.0
Requires-Dist: pythonnet>=3.0.5
Requires-Dist: requests>=2.31.0
Provides-Extra: dev
Requires-Dist: pytest>=8.0.0; extra == 'dev'
